bfg/__init__.py
bfg/bfg.py
bfg/utils.py
btrfsgit-9000.0.2.dist-info/entry_points.txt
btrfsgit-9000.0.2.dist-info/LICENSE
btrfsgit-9000.0.2.dist-info/WHEEL
btrfsgit-9000.0.2.dist-info/METADATA
btrfsgit-9000.0.2.dist-info/RECORD
